sathurangamPy/__init__.py
sathurangamPy/sathurangamPy.py
sathurangam-0.0.3.dist-info/LICENSE
sathurangam-0.0.3.dist-info/METADATA
sathurangam-0.0.3.dist-info/WHEEL
sathurangam-0.0.3.dist-info/top_level.txt
sathurangam-0.0.3.dist-info/RECORD
